{"230900":{"l":"halvsløj","v":[],"lg":"da","c":92596,"ind":1},"230901":{"l":"halvsove","v":[],"lg":"da","c":92597,"ind":1},"230902":{"l":"halvstik","v":[],"lg":"da","c":54662,"ind":1},"230903":{"l":"halvstiv","v":[],"lg":"da","c":92598,"ind":1,"ex":["han dansede rundt på sine <b>halvstive</b> ben"]},"230904":{"l":"halvstiv","v":[],"lg":"da","c":92599,"ind":2,"ex":["I drivhuset er det tid til en grundig rengøring med lunkent vand, brun sæbe og en <b>halvstiv</b> børste"]},"230905":{"l":"halvstor","v":[],"lg":"da","c":92600,"ind":1,"ex":["Hun opdagede hunden med det samme. Det var en <b>halvstor</b> hvalp — grå og forpjusket"]},"230906":{"l":"halvstrømpe","v":[],"lg":"da","c":92601,"ind":1,"sr":[{"t":"syn","to":239604}]},"230907":{"l":"halvstuderet røver","v":[],"lg":"da","c":92602,"ind":1},"230908":{"l":"halvsur","v":[],"lg":"da","c":92603,"ind":1},"230909":{"l":"halvsyvtiden","v":[],"lg":"da","c":92604,"ind":1},"230910":{"l":"halvsøskende","v":[],"lg":"da","c":92605,"ind":1,"ex":["Min kæreste har en masse <b>halvsøskende</b>, hans forældre er skilt og gift igen hver for sig"]},"230911":{"l":"halvsøster","v":[],"lg":"da","c":92606,"ind":1,"ex":["for åben skærm [blev han] forenet med en <b>halvsøster</b>, han ikke anede, han havde"]},"230912":{"l":"halvsøvn","v":[],"lg":"da","c":92607,"ind":1,"ex":["Senere vrælede hun, så .. hunden forskrækket vågnede op af sin <b>halvsøvn</b>"]},"230913":{"l":"halvt menneske","v":[],"lg":"da","c":92608,"ind":1},"230914":{"l":"halvtag","v":[],"lg":"da","c":92609,"ind":1,"ex":["selvom det var sidst på eftermiddagen bagte solen, og de holdt sig omhyggeligt langt inde under <b>halvtaget</b>"]},"230915":{"l":"halvtante","v":[],"lg":"da","c":92610,"ind":1},"230916":{"l":"halvtid","v":[],"lg":"da","c":92611,"ind":1,"ex":["Jeg måtte starte de første måneder på <b>halvtid</b>, fordi jeg ikke havde kræfter til fuldtid på mit arbejde"]},"230917":{"l":"halvtidsansat","v":[],"lg":"da","c":92612,"ind":1,"ex":["Bare på den anden siden af Sundet i Sverige er det almindeligt, at professorer er <b>halvtidsansatte</b> i medicinalfirmaer"]},"230918":{"l":"halvtidsarbejde","v":[],"lg":"da","c":92512,"ind":1,"ex":["Hun ligner en million, mens hun henter og bringer ungerne til og fra skole og sport og passer sit moderne <b>halvtidsarbejde</b> på fuldtid"],"sr":[{"t":"syn","to":230807}]},"230919":{"l":"halvtidsjob","v":[],"lg":"da","c":92613,"ind":1},"230920":{"l":"halvtitiden","v":[],"lg":"da","c":92614,"ind":1},"230921":{"l":"halvtolv","v":[],"lg":"da","c":92615,"ind":1,"ex":["kortene er fundet frem og der spilles et 'slag' casino, 500, <b>halvtolv</b> osv. sammen med ungerne"]},"230922":{"l":"halvtolvtiden","v":[],"lg":"da","c":92616,"ind":1},"230923":{"l":"halvtom","v":[],"lg":"da","c":92617,"ind":1,"ex":["Trods fine anmeldelser går stykket for <b>halvtomme</b> sale"]},"230924":{"l":"halvtosset","v":[],"lg":"da","c":92618,"ind":1,"sr":[{"t":"syn","to":267014}]},"230925":{"l":"halvtotalbillede","v":[],"lg":"da","c":92619,"ind":1,"ex":["Ved et tryk på en knap kan kameramanden altså vælge imellem et stort bredt totalbillede eller et mellemstort <b>halvtotalbillede</b> eller et nærbillede"]},"230926":{"l":"halvtotiden","v":[],"lg":"da","c":92620,"ind":1},"230927":{"l":"halvtredser","v":[],"lg":"da","c":92621,"ind":1},"230928":{"l":"halvtredser","v":[],"lg":"da","c":92622,"ind":2,"ex":["Hans seneste scoop var en musikvideo indkøbt på en jysk benzintank for bare en <b>halvtredser</b>"],"sr":[{"t":"syn","to":230936}]},"230929":{"l":"halvtredser","v":[],"lg":"da","c":92623,"ind":3},"230930":{"l":"halvtredser","v":[],"lg":"da","c":92624,"ind":4,"ex":["<b>Halvtredserne</b> var den kolde krigs årti"]},"230931":{"l":"halvtredskroneseddel","v":[],"lg":"da","c":92625,"ind":1},"230932":{"l":"halvtredsårig","v":[],"lg":"da","c":92626,"ind":1,"sr":[{"t":"syn","to":230934}]},"230933":{"l":"halvtredsårig","v":[],"lg":"da","c":92627,"ind":2},"230934":{"l":"halvtredsårs","v":[],"lg":"da","c":92626,"ind":1,"sr":[{"t":"syn","to":230932}]},"230935":{"l":"halvtredsårsdag","v":[],"lg":"da","c":92628,"ind":1},"230936":{"l":"halvtreller","v":[],"lg":"da","c":92622,"ind":1,"ex":["Væk er tidligere tiders nødhjælpsmode a la tweedjakkesæt til en <b>halvtreller</b>, og inde er i stedet .. redesign og nøje udvalgt genbrug"],"sr":[{"t":"syn","to":230928}]},"230937":{"l":"halvtretiden","v":[],"lg":"da","c":92629,"ind":1},"230938":{"l":"halvtør","v":[],"lg":"da","c":92630,"ind":1,"ex":["Kombinationen Tog + Mad fik mange til at tænke på en <b>halvtør</b>, slatten og dyr sandwich viklet ind i metervis af plastfolie"]},"230939":{"l":"halvvejen","v":[],"lg":"da","c":92631,"ind":1,"ex":["Under mottoet 'Hele Danmark mødes på <b>halvvejen</b> i Odense' satser den fynske hovedstad på at trække turister og penge til byen"]},"230940":{"l":"halvvæg","v":[],"lg":"da","c":92632,"ind":1,"ex":["De to rum er knyttet tæt sammen, kun adskilt af en <b>halvvæg</b>, der gemmer på kogesektionen og brændeovnens skorsten"]},"230941":{"l":"halvår","v":[],"lg":"da","c":92633,"ind":1,"ex":["Fødselstallet steg kraftigt i sidste <b>halvår</b> af 1986"]},"230942":{"l":"halvårlig","v":[],"lg":"da","c":92634,"ind":1,"ex":["Man kan selvfølgelig tegne sig for et <b>halvårligt</b> medlemskab, men de seriøse tager et helt år med det samme"]},"230943":{"l":"halvårlig","v":[],"lg":"da","c":92635,"ind":2,"ex":["det belaster de ældre pensionisters økonomi med 500 kroner om året, hvis man har 2 <b>halvårlige</b> tandlægebesøg"]},"230944":{"l":"halvårs","v":[],"lg":"da","c":92636,"ind":1,"ex":["[Uddannelsen] består af fire <b>halvårs</b> skoleophold, afbrudt af fire praktikperioder"]},"230945":{"l":"halvårsrapport","v":[],"lg":"da","c":92637,"ind":1,"ex":["I forbindelse med aflæggelsen af <b>halvårsrapporten</b> opjusterede ledelsen forventningerne til 2015/ 16"]},"230946":{"l":"halvårsregnskab","v":[],"lg":"da","c":92638,"ind":1,"ex":["Det store danske bryggeriselskab skal forsøge at rejse sig efter et skuffende <b>halvårsregnskab</b>, hvor selskabet måtte nedjustere sine forventninger"]},"230947":{"l":"halvårsresultat","v":[],"lg":"da","c":92639,"ind":1,"ex":["LEGO er i dag kommet med <b>halvårsresultat</b>. LEGO Koncernens nettoomsætning for første halvår af 2010 blev 34% højere end samme periode året før"]},"230948":{"l":"halvædelsten","v":[],"lg":"da","c":92640,"ind":1,"ex":["Den blå baggrundsfarve var fremstillet af <b>halvædelstenen</b> lapis lazuli"]},"230949":{"l":"halvø","v":[],"lg":"da","c":92641,"ind":1,"ex":["Korinther-kanalen .. gør det muligt at stikke genvej mellem det græske fastland og <b>halvøen</b> Peloponnes"]},"230950":{"l":"ham","v":[],"lg":"da","c":38791,"ind":1,"ex":["uden <b>hammen</b> viste sælen sig at være den smukkeste pige"],"sr":[{"t":"syn","to":219260}]},"230951":{"l":"hamburger","v":[],"lg":"da","c":78887,"ind":1,"ex":["Jeg går ind til Åke i grillbaren og får mig en <b>hamburger</b>. Vil du have én med?"],"sr":[{"t":"syn","to":215069},{"t":"syn","to":215650}]},"230952":{"l":"hamburger","v":[],"lg":"da","c":92642,"ind":2},"230953":{"l":"hamburgerryg","v":[],"lg":"da","c":92643,"ind":1,"ex":["Kent, vi skal ha' <b>hamburgerryg</b> med grønlangkål"]},"230954":{"l":"hamle op med","v":[],"lg":"da","c":92644,"ind":1},"230955":{"l":"Hammel","v":[],"lg":"da","c":92645,"ind":1},"230956":{"l":"hammer","v":[],"lg":"da","c":13084,"ind":1,"ex":["dommeren knalder <b>hammeren</b> i skranken for at få tilhørerne til at være stille"]},"230957":{"l":"hammer","v":[],"lg":"da","c":92646,"ind":2,"ex":["[trommehindens] svingninger overføres til <b>hammeren</b>, som igen sætter ambolten og stigbøjlen i bevægelse"]},"230958":{"l":"hammer","v":[],"lg":"da","c":92647,"ind":3,"ex":["I andet forsøg landede <b>hammeren</b> på 67 meter"]},"230959":{"l":"hammer","v":[],"lg":"da","c":92648,"ind":4,"ex":["Kuglehovedet [: på skrivemaskiner] er senere erstattet af et roterende skrivehjul som slås an af en elektromagnetisk <b>hammer</b>"]},"230960":{"l":"hammerfed","v":[],"lg":"da","c":92649,"ind":1,"sr":[{"t":"syn","to":247939},{"t":"syn","to":231870},{"t":"syn","to":239685},{"t":"syn","to":264620}]},"230961":{"l":"hammerfed","v":[],"lg":"da","c":92650,"ind":2},"230962":{"l":"hammergod","v":[],"lg":"da","c":77962,"ind":1,"ex":["den næsten altid smilende skuespiller ser <b>hammergodt</b> ud i bukser med vidde forneden, bar mave og blå top"],"sr":[{"t":"syn","to":219482},{"t":"syn","to":214015},{"t":"syn","to":239370},{"t":"syn","to":264624},{"t":"syn","to":237587},{"t":"syn","to":271608},{"t":"syn","to":266708}]},"230963":{"l":"hammerhaj","v":[],"lg":"da","c":92651,"ind":1},"230964":{"l":"hammerhoved","v":[],"lg":"da","c":92652,"ind":1},"230965":{"l":"hammerkast","v":[],"lg":"da","c":92653,"ind":1,"ex":["Ifølge overleveringerne blev konceptet bag <b>hammerkast</b> lanceret af den keltiske kriger Culchulainn, der ca. 2.000 år f. Kr. tog fat i akslen til et vognhjul og slyngede hjulet af sted"]},"230966":{"l":"hammerkaster","v":[],"lg":"da","c":92654,"ind":1,"ex":["De dopingdømte olympiske guldvindere fra Ungarn, diskoskasteren Robert Fazekas og <b>hammerkasteren</b> Adrian Anus, har fået to års karantæne af det ungarske atletikforbund"]},"230967":{"l":"hammerklaver","v":[],"lg":"da","c":92655,"ind":1},"230968":{"l":"Hammershøj","v":[],"lg":"da","c":92656,"ind":1},"230969":{"l":"hammerslag","v":[],"lg":"da","c":92657,"ind":1,"ex":["ud over selve spændingen ved <b>hammerslaget</b> er der både oplevelser og smukke ting at hente"]},"230970":{"l":"hammerslag","v":[],"lg":"da","c":92658,"ind":2,"ex":["Nu kan man se, hvordan de mange kiler og de hårde <b>hammerslag</b> får den store træstamme til at dele sig"]},"230971":{"l":"hammertå","v":[],"lg":"da","c":92659,"ind":1},"230972":{"l":"hammondorgel","v":[],"lg":"da","c":92660,"ind":1,"ex":["Georgie Fame .. bidrager med sit vidunderlige, uldne <b>hammondorgel</b>"]},"230973":{"l":"hamp","v":[],"lg":"da","c":79758,"ind":1,"ex":["<b>Hamp</b> vokser vildt i Centralasien"],"sr":[{"t":"syn","to":216058}]},"230974":{"l":"hamp","v":[],"lg":"da","c":92661,"ind":2},"230975":{"l":"hamp","v":[],"lg":"da","c":79757,"ind":3,"ex":["De ældste fund, der viser, at man har røget <b>hamp</b>, er fra ca. 500 før vor tid"],"sr":[{"t":"syn","to":216057}]},"230976":{"l":"hampefrø","v":[],"lg":"da","c":92662,"ind":1},"230977":{"l":"Hampen","v":[],"lg":"da","c":92663,"ind":1},"230978":{"l":"hampeplante","v":[],"lg":"da","c":92664,"ind":1},"230979":{"l":"hamre","v":[],"lg":"da","c":92665,"ind":1,"ex":["ANC <b>hamrer</b> løs på regeringen med anklagerne om korruption og uærlighed"]},"230980":{"l":"hamre","v":[],"lg":"da","c":92666,"ind":2,"ex":["styreluften fra kommandobroen til maskinrummet [svigtede]. Derfor fortsatte færgen med fuld fart og <b>hamrede</b> ind i bolværket"]},"230981":{"l":"hamre","v":[],"lg":"da","c":92667,"ind":3,"ex":["pladen <b>hamrede</b> direkte ind på førstepladsen i USA"]},"230982":{"l":"hamre","v":[],"lg":"da","c":92668,"ind":4,"ex":["En dyb, knitrende, <b>hamrende</b> lyd, en bil og glas, der knuses, skrig overalt"]},"230983":{"l":"hamre","v":[],"lg":"da","c":92669,"ind":5},"230984":{"l":"hamre ud","v":[],"lg":"da","c":92670,"ind":1,"sr":[{"t":"syn","to":277916}]},"230985":{"l":"hamskifte","v":[],"lg":"da","c":92671,"ind":1,"ex":["[partiet] skal gennemgå et kraftigt <b>hamskifte</b> og tilbringe nogle år i opposition"]},"230986":{"l":"hamster","v":[],"lg":"da","c":92672,"ind":1,"ex":["Foruden Bølle har jeg en anden kat, fire undulater og to <b>hamstere</b>. De går alle frit rundt derhjemme"]},"230987":{"l":"hamstre","v":[],"lg":"da","c":92673,"ind":1,"ex":["De, der har opkøbt eller <b>hamstret</b> olie i forventning om at priserne ville nå nye astronomiske højder, bliver skuffede"]},"230988":{"l":"han","v":[],"lg":"da","c":92674,"ind":1,"sr":[{"t":"syn","to":231097}]},"230989":{"l":"han","v":[],"lg":"da","c":92675,"ind":2,"ex":["Det sidste tal i vores CPR-nummer angiver som bekendt det køn vi har. Lige tal for hunner -- ulige for <b>hanner</b>"]},"230990":{"l":"han (hun, ..) snakker, og røven går","v":[],"lg":"da","c":92676,"ind":1},"230991":{"l":"han er ikke ked af det","v":[],"lg":"da","c":92677,"ind":1},"230992":{"l":"hanblomst","v":[],"lg":"da","c":92678,"ind":1,"ex":["<b>Hanblomsten</b> [: hos dunhammer] består blot af nogle få støvblade og hunblomsten af en énfrøet støvvej med lang griffel"]},"230993":{"l":"handel","v":[],"lg":"da","c":3904,"ind":1,"ex":["Det viste sig, at de forretninger, han lavede, var <b>handel</b> med brandvarme hælervarer"]},"230994":{"l":"handel","v":[],"lg":"da","c":92679,"ind":2,"ex":["Fra på torsdag den 8. oktober er det nye frimærke i <b>handelen</b>"],"sr":[{"t":"syn","to":247354}]},"230995":{"l":"handelsaftale","v":[],"lg":"da","c":92680,"ind":1,"ex":["USA og Rumænien vil .. indgå en ny <b>handelsaftale</b>, der åbner mulighed for, at rumænske varer kan sælges på det amerikanske marked med laveste import- og toldafgift"]},"230996":{"l":"handelsagent","v":[],"lg":"da","c":72894,"ind":1,"sr":[{"t":"syn","to":207660}]},"230997":{"l":"handelsagentur","v":[],"lg":"da","c":92681,"ind":1},"230998":{"l":"handelsakademi","v":[],"lg":"da","c":92682,"ind":1},"230999":{"l":"handelsbalance","v":[],"lg":"da","c":92683,"ind":1,"ex":["bevidst satsning fra forbrugernes side på at købe danske varer frem for importerede har afgørende indflydelse på <b>handelsbalancen</b>"]}}