{"583700":{"l":"onyx marble","v":[],"lg":"en","c":62535,"ind":1,"sr":[{"t":"syn","to":571518},{"t":"syn","to":456444},{"t":"syn","to":585008}]},"583701":{"l":"onyxis","v":[],"lg":"en","c":179518,"ind":1,"sr":[{"t":"syn","to":550242}]},"583702":{"l":"oocyte","v":[],"lg":"en","c":40338,"ind":1},"583703":{"l":"oodles","v":[],"lg":"en","c":15958,"ind":1,"sr":[{"t":"syn","to":508057},{"t":"syn","to":535043},{"t":"syn","to":540852},{"t":"syn","to":559233},{"t":"syn","to":563462},{"t":"syn","to":564536},{"t":"syn","to":593403},{"t":"syn","to":604676},{"t":"syn","to":616443},{"t":"syn","to":617405},{"t":"syn","to":625364},{"t":"syn","to":631242},{"t":"syn","to":644732},{"t":"syn","to":657131}]},"583704":{"l":"oogenesis","v":[],"lg":"en","c":40316,"ind":1},"583705":{"l":"ooh","v":[],"lg":"en","c":160222,"ind":1,"sr":[{"t":"syn","to":452317}]},"583706":{"l":"oology","v":[],"lg":"en","c":186085,"ind":1},"583707":{"l":"oolong","v":[],"lg":"en","c":186086,"ind":1},"583708":{"l":"Oom Paul Kruger","v":[],"lg":"en","c":180923,"ind":1,"sr":[{"t":"syn","to":557777},{"t":"syn","to":632551}]},"583709":{"l":"oomph","v":[],"lg":"en","c":25155,"ind":1,"sr":[{"t":"syn","to":509912},{"t":"syn","to":594329},{"t":"syn","to":594330},{"t":"syn","to":664085}]},"583710":{"l":"oomph","v":[],"lg":"en","c":45456,"ind":2,"sr":[{"t":"syn","to":503143},{"t":"syn","to":503147},{"t":"syn","to":620852}]},"583711":{"l":"Oomycetes","v":[],"lg":"en","c":65822,"ind":1,"sr":[{"t":"syn","to":487756}]},"583712":{"l":"oophorectomy","v":[],"lg":"en","c":146238,"ind":1,"sr":[{"t":"syn","to":586044}]},"583713":{"l":"oophoritis","v":[],"lg":"en","c":54984,"ind":1},"583714":{"l":"oophorosalpingectomy","v":[],"lg":"en","c":186087,"ind":1},"583715":{"l":"Oort","v":[],"lg":"en","c":180167,"ind":1,"sr":[{"t":"syn","to":553804},{"t":"syn","to":553806}]},"583716":{"l":"Oort cloud","v":[],"lg":"en","c":154261,"ind":1},"583717":{"l":"oosphere","v":[],"lg":"en","c":40041,"ind":1},"583718":{"l":"oospore","v":[],"lg":"en","c":40339,"ind":1},"583719":{"l":"ootid","v":[],"lg":"en","c":186088,"ind":1},"583720":{"l":"ooze","v":[],"lg":"en","c":11807,"ind":1,"sr":[{"t":"syn","to":535425},{"t":"syn","to":535564},{"t":"syn","to":535571},{"t":"syn","to":537853},{"t":"syn","to":538208},{"t":"syn","to":575665},{"t":"syn","to":625464},{"t":"syn","to":625762}]},"583721":{"l":"ooze","v":[],"lg":"en","c":186089,"ind":2,"sr":[{"t":"-der","to":583729},{"t":"der","to":583722},{"t":"der","to":583723},{"t":"syn","to":583728},{"t":"syn","to":618982}]},"583722":{"l":"ooze","v":[],"lg":"en","c":24730,"ind":1,"sr":[{"t":"-der","to":583721},{"t":"-der","to":583728},{"t":"syn","to":517293},{"t":"syn","to":517296},{"t":"syn","to":583725},{"t":"syn","to":646334}]},"583723":{"l":"ooze","v":[],"lg":"en","c":18883,"ind":2,"sr":[{"t":"-der","to":583721},{"t":"-der","to":583728},{"t":"syn","to":618981}]},"583724":{"l":"ooze leather","v":[],"lg":"en","c":63001,"ind":1},"583725":{"l":"ooze out","v":[],"lg":"en","c":24730,"ind":1,"sr":[{"t":"syn","to":517293},{"t":"syn","to":517296},{"t":"syn","to":583722},{"t":"syn","to":646334}]},"583726":{"l":"ooze through","v":[],"lg":"en","c":186090,"ind":1,"ex":["Blood <b>oozed through</b> the bandage"]},"583727":{"l":"oozing","v":[],"lg":"en","c":186091,"ind":1,"sr":[{"t":"syn","to":583729},{"t":"syn","to":618983}]},"583728":{"l":"oozing","v":[],"lg":"en","c":186089,"ind":1,"sr":[{"t":"der","to":583722},{"t":"der","to":583723},{"t":"syn","to":583721},{"t":"syn","to":618982}]},"583729":{"l":"oozy","v":["oozier","ooziest"],"lg":"en","c":186091,"ind":1,"sr":[{"t":"der","to":583721},{"t":"syn","to":583727},{"t":"syn","to":618983}]},"583730":{"l":"op art","v":[],"lg":"en","c":186092,"ind":1},"583731":{"l":"opacification","v":[],"lg":"en","c":51095,"ind":1,"sr":[{"t":"der","to":583732}]},"583732":{"l":"opacify","v":[],"lg":"en","c":186093,"ind":1,"ex":["the tissue in the eye's cornea may <b>opacify</b> and the patient may go blind"],"sr":[{"t":"-der","to":583731}]},"583733":{"l":"opacify","v":[],"lg":"en","c":186094,"ind":2,"ex":["The glass was <b>opacified</b> for greater privacy"]},"583734":{"l":"opacity","v":[],"lg":"en","c":40043,"ind":1,"sr":[{"t":"-der","to":583749},{"t":"ant","to":487626},{"t":"syn","to":583753}]},"583735":{"l":"opacity","v":[],"lg":"en","c":40044,"ind":2,"sr":[{"t":"-der","to":583750},{"t":"syn","to":583754}]},"583736":{"l":"opacity","v":[],"lg":"en","c":40045,"ind":3,"sr":[{"t":"-der","to":583749},{"t":"ant","to":646236}]},"583737":{"l":"opah","v":[],"lg":"en","c":62049,"ind":1,"sr":[{"t":"syn","to":558661},{"t":"syn","to":574500}]},"583738":{"l":"opal","v":[],"lg":"en","c":2718,"ind":1,"sr":[{"t":"der","to":583747},{"t":"der","to":583748}]},"583739":{"l":"opal glass","v":[],"lg":"en","c":51101,"ind":1,"sr":[{"t":"syn","to":572244}]},"583740":{"l":"opalesce","v":[],"lg":"en","c":55333,"ind":1,"ex":["This nitrate <b>opalesces</b> under certain conditions"],"sr":[{"t":"-der","to":583743},{"t":"-der","to":583742}]},"583741":{"l":"opalesce","v":[],"lg":"en","c":55334,"ind":2,"ex":["Distant clouds <b>opalesce</b> like pale brocade","raindrops caught in a sunbeam seem to <b>opalesce</b>"],"sr":[{"t":"-der","to":583743},{"t":"-der","to":583742}]},"583742":{"l":"opalescence","v":[],"lg":"en","c":35455,"ind":1,"sr":[{"t":"-der","to":583743},{"t":"der","to":583740},{"t":"der","to":583741},{"t":"syn","to":552484}]},"583743":{"l":"opalescent","v":[],"lg":"en","c":35453,"ind":1,"ex":["a milky <b>opalescent</b> (or opaline) luster"],"sr":[{"t":"der","to":583742},{"t":"der","to":583740},{"t":"der","to":583741},{"t":"syn","to":552485},{"t":"syn","to":577056},{"t":"syn","to":583744},{"t":"syn","to":589952}]},"583744":{"l":"opaline","v":[],"lg":"en","c":35453,"ind":1,"sr":[{"t":"syn","to":552485},{"t":"syn","to":577056},{"t":"syn","to":583743},{"t":"syn","to":589952}]},"583745":{"l":"opalise","v":[],"lg":"en","c":186095,"ind":1,"sr":[{"t":"syn","to":583747}]},"583746":{"l":"opalise","v":[],"lg":"en","c":186096,"ind":2,"sr":[{"t":"syn","to":583748}]},"583747":{"l":"opalize","v":[],"lg":"en","c":186095,"ind":1,"ex":["<b>opalized</b> tree trunks"],"sr":[{"t":"-der","to":583738},{"t":"syn","to":583745}]},"583748":{"l":"opalize","v":[],"lg":"en","c":186096,"ind":2,"sr":[{"t":"-der","to":583738},{"t":"syn","to":583746}]},"583749":{"l":"opaque","v":[],"lg":"en","c":40042,"ind":1,"ex":["<b>opaque</b> windows of the jail","<b>opaque</b> to X-rays"],"sr":[{"t":"ant","to":488041},{"t":"der","to":583734},{"t":"der","to":583736},{"t":"der","to":583753}]},"583750":{"l":"opaque","v":[],"lg":"en","c":34754,"ind":2,"sr":[{"t":"der","to":583735},{"t":"der","to":583754},{"t":"-ptr","to":583752},{"t":"syn","to":651376}]},"583751":{"l":"opaque gem","v":[],"lg":"en","c":30424,"ind":1},"583752":{"l":"opaquely","v":[],"lg":"en","c":50478,"ind":1,"ex":["he referred <b>opaquely</b> to her recent past"],"sr":[{"t":"ptr","to":583750}]},"583753":{"l":"opaqueness","v":[],"lg":"en","c":40043,"ind":1,"sr":[{"t":"-der","to":583749},{"t":"syn","to":583734}]},"583754":{"l":"opaqueness","v":[],"lg":"en","c":40044,"ind":2,"sr":[{"t":"-der","to":583750},{"t":"syn","to":583735}]},"583755":{"l":"OPCW","v":[],"lg":"en","c":186097,"ind":1,"sr":[{"t":"syn","to":584963}]},"583756":{"l":"OPEC","v":[],"lg":"en","c":2719,"ind":1,"sr":[{"t":"syn","to":584966}]},"583757":{"l":"Opel","v":[],"lg":"en","c":186098,"ind":1,"sr":[{"t":"syn","to":660683}]},"583758":{"l":"open","v":[],"lg":"en","c":48039,"ind":1,"ex":["the job is still <b>open</b>"]},"583759":{"l":"open","v":[],"lg":"en","c":39669,"ind":2,"ex":["an <b>open</b> protest","an <b>open</b> letter to the editor"],"sr":[{"t":"der","to":583779}]},"583760":{"l":"open","v":[],"lg":"en","c":28612,"ind":3,"ex":["<b>open</b> to the weather","an <b>open</b> wound"],"sr":[{"t":"syn","to":516858}]},"583761":{"l":"open","v":[],"lg":"en","c":67888,"ind":4,"sr":[{"t":"der","to":583886},{"t":"syn","to":606420}]},"583762":{"l":"open","v":[],"lg":"en","c":39671,"ind":5,"ex":["<b>open</b> season","an <b>open</b> economy"],"sr":[{"t":"der","to":583780}]},"583763":{"l":"open","v":[],"lg":"en","c":39673,"ind":6,"ex":["the letter was already <b>open</b>"],"sr":[{"t":"syn","to":583857}]},"583764":{"l":"open","v":[],"lg":"en","c":39675,"ind":7,"ex":["an <b>open</b> question"],"sr":[{"t":"syn","to":650329},{"t":"syn","to":650650},{"t":"syn","to":652325}]},"583765":{"l":"open","v":[],"lg":"en","c":58381,"ind":8,"ex":["an <b>open</b> texture"],"sr":[{"t":"syn","to":564290}]},"583766":{"l":"open","v":[],"lg":"en","c":55772,"ind":9,"ex":["<b>open</b> to interpretation","an issue <b>open</b> to question"],"sr":[{"t":"syn","to":480320},{"t":"syn","to":635143}]},"583767":{"l":"open","v":[],"lg":"en","c":186099,"ind":10,"ex":["an <b>open</b> shop employs nonunion workers"]},"583768":{"l":"open","v":[],"lg":"en","c":34815,"ind":11,"ex":["an <b>open</b> city","<b>open</b> to attack"],"sr":[{"t":"syn","to":463545},{"t":"syn","to":650342},{"t":"syn","to":650343}]},"583769":{"l":"open","v":[],"lg":"en","c":39678,"ind":12,"ex":["the stores are <b>open</b>"]},"583770":{"l":"open","v":[],"lg":"en","c":165541,"ind":13,"ex":["an <b>open</b> and trusting nature"],"sr":[{"t":"der","to":583887},{"t":"syn","to":479944},{"t":"syn","to":540925}]},"583771":{"l":"open","v":[],"lg":"en","c":186100,"ind":14,"ex":["the clarity and resonance of an <b>open</b> tone","her natural and <b>open</b> response"],"sr":[{"t":"der","to":583886}]},"583772":{"l":"open","v":[],"lg":"en","c":21348,"ind":15,"ex":["<b>open</b> waters","the <b>open</b> countryside"],"sr":[{"t":"der","to":583782},{"t":"der","to":583888},{"t":"syn","to":488052}]},"583773":{"l":"open","v":[],"lg":"en","c":39680,"ind":16,"ex":["an <b>open</b> door","they left the door <b>open</b>"],"sr":[{"t":"ant","to":622824},{"t":"syn","to":650960}]},"583774":{"l":"open","v":[],"lg":"en","c":12195,"ind":17,"ex":["<b>open</b> drains","the road is <b>open</b> to traffic","<b>open</b> ranks"],"sr":[{"t":"ant","to":488675},{"t":"-ptr","to":583884}]},"583775":{"l":"open","v":[],"lg":"en","c":39681,"ind":18,"ex":["keep your eyes <b>open</b>"],"sr":[{"t":"ant","to":488676},{"t":"syn","to":583859}]},"583776":{"l":"open","v":[],"lg":"en","c":186101,"ind":19,"ex":["an <b>open</b> boat","an <b>open</b> fire","<b>open</b> sports cars"],"sr":[{"t":"der","to":583781}]},"583777":{"l":"open","v":[],"lg":"en","c":186102,"ind":20,"sr":[{"t":"ant","to":488678}]},"583778":{"l":"open","v":[],"lg":"en","c":12214,"ind":21,"ex":["<b>open</b> ballots"],"sr":[{"t":"der","to":583887},{"t":"syn","to":586484}]},"583779":{"l":"open","v":[],"lg":"en","c":186103,"ind":1,"ex":["all the reports were out in the <b>open</b>"],"sr":[{"t":"-der","to":583759},{"t":"syn","to":636912}]},"583780":{"l":"open","v":[],"lg":"en","c":40049,"ind":2,"sr":[{"t":"-der","to":583762}]},"583781":{"l":"open","v":[],"lg":"en","c":14430,"ind":3,"ex":["camping in the <b>open</b>"],"sr":[{"t":"-der","to":583776},{"t":"syn","to":583795},{"t":"syn","to":585722},{"t":"syn","to":585781}]},"583782":{"l":"open","v":[],"lg":"en","c":167305,"ind":4,"ex":["finally broke out of the forest into the <b>open</b>"],"sr":[{"t":"-der","to":583772},{"t":"syn","to":488057}]},"583783":{"l":"open","v":[],"lg":"en","c":24531,"ind":1,"ex":["This <b>opens</b> up new possibilities"],"sr":[{"t":"-der","to":583868},{"t":"syn","to":583819}]},"583784":{"l":"open","v":[],"lg":"en","c":24532,"ind":2,"ex":["an opportunity <b>opened</b> up"],"sr":[{"t":"-der","to":583868},{"t":"syn","to":583820}]},"583785":{"l":"open","v":[],"lg":"en","c":142499,"ind":3,"ex":["Kasparov <b>opened</b> with a standard opening"],"sr":[{"t":"-der","to":583869}]},"583786":{"l":"open","v":[],"lg":"en","c":2357,"ind":4,"ex":["Mary <b>opened</b> the car door"],"sr":[{"t":"-der","to":583860},{"t":"-der","to":583862},{"t":"-der","to":583870},{"t":"-der","to":583871},{"t":"ant","to":488618},{"t":"syn","to":583822}]},"583787":{"l":"open","v":[],"lg":"en","c":4315,"ind":5,"ex":["The door <b>opened</b>"],"sr":[{"t":"-der","to":583871},{"t":"ant","to":488619},{"t":"syn","to":583823}]},"583788":{"l":"open","v":[],"lg":"en","c":5347,"ind":6,"ex":["<b>open</b> the map"],"sr":[{"t":"-der","to":583871},{"t":"syn","to":630451},{"t":"syn","to":630461},{"t":"syn","to":651040}]},"583789":{"l":"open","v":[],"lg":"en","c":60329,"ind":7,"sr":[{"t":"ant","to":488626}]},"583790":{"l":"open","v":[],"lg":"en","c":3882,"ind":8,"ex":["He <b>opened</b> the meeting with a long speech"],"sr":[{"t":"-der","to":583861},{"t":"-der","to":583869},{"t":"-der","to":583879},{"t":"ant","to":488628}]},"583791":{"l":"open","v":[],"lg":"en","c":2218,"ind":9,"ex":["<b>open</b> a business"],"sr":[{"t":"-der","to":583869},{"t":"-der","to":583879},{"t":"ant","to":488629},{"t":"syn","to":583825}]},"583792":{"l":"open","v":[],"lg":"en","c":70072,"ind":10,"ex":["The bedrooms <b>open</b> into the hall"],"sr":[{"t":"-der","to":583873},{"t":"-der","to":583875},{"t":"-der","to":583880}]},"583793":{"l":"open account","v":[],"lg":"en","c":22075,"ind":1,"sr":[{"t":"syn","to":484530},{"t":"syn","to":496689}]},"583794":{"l":"open account","v":[],"lg":"en","c":186104,"ind":2},"583795":{"l":"open air","v":[],"lg":"en","c":14430,"ind":1,"ex":["the concert was held in the <b>open air</b>"],"sr":[{"t":"syn","to":583781},{"t":"syn","to":585722},{"t":"syn","to":585781}]},"583796":{"l":"open chain","v":[],"lg":"en","c":186105,"ind":1,"sr":[{"t":"ant","to":488680}]},"583797":{"l":"open circuit","v":[],"lg":"en","c":186106,"ind":1,"sr":[{"t":"ant","to":488681}]},"583798":{"l":"open door","v":[],"lg":"en","c":186107,"ind":1,"ex":["he maintained an <b>open door</b> for all employees"]},"583799":{"l":"open door","v":[],"lg":"en","c":186108,"ind":2,"sr":[{"t":"syn","to":583836}]}}